phardwareitk/Dependencies.py
phardwareitk/LIB.py
phardwareitk/__init__.py
phardwareitk/CLI/__init__.py
phardwareitk/CLI/cliToolKit.py
phardwareitk/ErrorSystem/ErrorSystem.py
phardwareitk/ErrorSystem/__init__.py
phardwareitk/Extensions/C.py
phardwareitk/Extensions/C_IO.py
phardwareitk/Extensions/HyperIn.py
phardwareitk/Extensions/HyperOut.py
phardwareitk/Extensions/HyperPython.py
phardwareitk/Extensions/Windows.py
phardwareitk/Extensions/__init__.py
phardwareitk/FileSystem/FileSystem.py
phardwareitk/FileSystem/__init__.py
phardwareitk/GPU/SysInfo.py
phardwareitk/GPU/__init__.py
phardwareitk/GPU/IntelUHD/__init__.py
phardwareitk/GPU/StressTester/run.py
phardwareitk/GUI/__init__.py
phardwareitk/GUI/gui.py
phardwareitk/GUI/gui_sdl.py
phardwareitk/HGame/__init__.py
phardwareitk/Memory/Memory.py
phardwareitk/Memory/__init__.py
phardwareitk/ModuleController/__init__.py
phardwareitk/ModuleController/main.py
phardwareitk/PENV/PBFS.py
phardwareitk/PENV/__init__.py
phardwareitk/PENV/bios.py
phardwareitk/PENV/framebuffer.py
phardwareitk/PENV/shared.py
phardwareitk/PLTEC/ASM.py
phardwareitk/PLTEC/Checker.py
phardwareitk/PLTEC/Linker.py
phardwareitk/PLTEC/Logger.py
phardwareitk/PLTEC/OBJECT.py
phardwareitk/PLTEC/Reader.py
phardwareitk/PLTEC/__init__.py
phardwareitk/PLTEC/main.py
phardwareitk/System/SysUsage.py
phardwareitk/System/__init__.py
phardwareitk-0.1.3.5.dist-info/LICENSE
phardwareitk-0.1.3.5.dist-info/METADATA
phardwareitk-0.1.3.5.dist-info/WHEEL
phardwareitk-0.1.3.5.dist-info/top_level.txt
phardwareitk-0.1.3.5.dist-info/RECORD
