Metadata-Version: 2.1
Name: phardwareitk
Version: 0.1.3.5
Summary: PHardwareITK, or Pheonix Hardware Interface Toolkit, is a comprehensive Python module. This toolkit provides a variety of functions and utilities to assist developers in creating complex systems/programs. It provides many toolkits and extensions for all your needs, want to emulate c in python that actually works well PHardwareITK got your back, want to make a OS easily, PHardwareITK got your back, please use the Github Wiki to learn more.
Author-email: Pheonix Studios <PheonixStudiosInfo@gmail.com>, Akshobhya Sasun <akshobhyasasun@gmail.com>
Project-URL: Homepage, https://github.com/AkshuDev/PHardwareITK
Project-URL: Issues, https://github.com/AkshuDev/PHardwareITK/issues
Project-URL: Wiki, https://github.com/AkshuDev/PHardwareITK/wiki
Project-URL: Website, https://paperexcahange.wixsite.com/pheonixstudios
Project-URL: Source, https://github.com/AkshuDev/PHardwareITK
Classifier: Programming Language :: Python :: 3
Classifier: License :: OSI Approved :: MIT License
Classifier: Operating System :: OS Independent
Requires-Python: >=3.7
License-File: LICENSE
